MANIFEST.in
README.rst
setup.py
docs/HISTORY.txt
docs/LICENSE.GPL
docs/LICENSE.txt
ftw/__init__.py
ftw.billboard.egg-info/PKG-INFO
ftw.billboard.egg-info/SOURCES.txt
ftw.billboard.egg-info/dependency_links.txt
ftw.billboard.egg-info/entry_points.txt
ftw.billboard.egg-info/namespace_packages.txt
ftw.billboard.egg-info/not-zip-safe
ftw.billboard.egg-info/requires.txt
ftw.billboard.egg-info/top_level.txt
ftw/billboard/__init__.py
ftw/billboard/config.py
ftw/billboard/configure.zcml
ftw/billboard/helpers.py
ftw/billboard/hooks.py
ftw/billboard/indexer.py
ftw/billboard/interfaces.py
ftw/billboard/lawgiver.zcml
ftw/billboard/testing.py
ftw/billboard/validators.py
ftw/billboard/Extensions/__init__.py
ftw/billboard/Extensions/install.py
ftw/billboard/browser/__init__.py
ftw/billboard/browser/ad.pt
ftw/billboard/browser/ad.py
ftw/billboard/browser/billboard_conditions.pt
ftw/billboard/browser/category.pt
ftw/billboard/browser/category.py
ftw/billboard/browser/category_listing.pt
ftw/billboard/browser/configure.zcml
ftw/billboard/browser/simple_upload.pt
ftw/billboard/browser/simple_upload.py
ftw/billboard/browser/resources/billboard.js
ftw/billboard/content/__init__.py
ftw/billboard/content/billboard_category.py
ftw/billboard/content/billboardad.py
ftw/billboard/content/configure.zcml
ftw/billboard/locales/ftw.billboard.pot
ftw/billboard/locales/de/LC_MESSAGES/ftw.billboard.po
ftw/billboard/locales/fr/LC_MESSAGES/ftw.billboard.po
ftw/billboard/portlets/__init__.py
ftw/billboard/portlets/actions.pt
ftw/billboard/portlets/actions.py
ftw/billboard/portlets/configure.zcml
ftw/billboard/profiles/default/catalog.xml
ftw/billboard/profiles/default/factorytool.xml
ftw/billboard/profiles/default/metadata.xml
ftw/billboard/profiles/default/portlets.xml
ftw/billboard/profiles/default/registry.xml
ftw/billboard/profiles/default/rolemap.xml
ftw/billboard/profiles/default/types.xml
ftw/billboard/profiles/default/workflows.xml
ftw/billboard/profiles/default/types/BillboardAd.xml
ftw/billboard/profiles/default/types/BillboardCategory.xml
ftw/billboard/profiles/uninstall/catalog.xml
ftw/billboard/profiles/uninstall/factorytool.xml
ftw/billboard/profiles/uninstall/portlets.xml
ftw/billboard/profiles/uninstall/registry.xml
ftw/billboard/profiles/uninstall/rolemap.xml
