Metadata-Version: 2.1
Name: ftw.billboard
Version: 1.6.0
Summary: Simple market place addon for plone.
Home-page: https://github.com/4teamwork/ftw.billboard
Author: 4teamwork AG
Author-email: mailto:info@4teamwork.ch
Maintainer: Julian Infanger
License: GPL2
Keywords: plone billboard ads advertisement ftw
Platform: UNKNOWN
Classifier: Framework :: Plone
Classifier: Framework :: Plone :: 4.3
Classifier: Framework :: Zope2
Classifier: Programming Language :: Python
Classifier: Topic :: Software Development :: Libraries :: Python Modules
Provides-Extra: tests
